python_project_helper/__init__.py
python_project_helper/__main__.py
python_project_helper/_version.py
python_project_helper-0.2.1.dist-info/LICENSE
python_project_helper-0.2.1.dist-info/METADATA
python_project_helper-0.2.1.dist-info/WHEEL
python_project_helper-0.2.1.dist-info/entry_points.txt
python_project_helper-0.2.1.dist-info/top_level.txt
python_project_helper-0.2.1.dist-info/RECORD
