Metadata-Version: 2.1
Name: python-project-helper
Version: 0.2.1
Author-email: Gregory Werbin <outthere@me.gregwerbin.com>
License: BSD 3-Clause License
Project-URL: Changelog, https://github.com/gwerbin/python-project-helper/blob/main/CHANGELOG.adoc
Project-URL: Source code (Github), https://github.com/gwerbin/python-project-helper
Project-URL: Source code (Sourcehut), https://git.sr.ht/~wintershadows/python-project-helper
Classifier: Programming Language :: Python
Classifier: Development Status :: 4 - Beta
Requires-Python: >=3.8
License-File: LICENSE
Requires-Dist: build
Provides-Extra: tests
Requires-Dist: pytest ~=7.0 ; extra == 'tests'
Requires-Dist: pytest-cov ; extra == 'tests'
Requires-Dist: pytest-mock ; extra == 'tests'
Requires-Dist: coverage ; extra == 'tests'
Requires-Dist: hypothesis ; extra == 'tests'
Requires-Dist: mypy ~=1.0 ; extra == 'tests'
